ai_journal_kit/__init__.py
ai_journal_kit/__main__.py
ai_journal_kit/cli/__init__.py
ai_journal_kit/cli/add_ide.py
ai_journal_kit/cli/app.py
ai_journal_kit/cli/customize_template.py
ai_journal_kit/cli/doctor.py
ai_journal_kit/cli/list_journals.py
ai_journal_kit/cli/move.py
ai_journal_kit/cli/setup.py
ai_journal_kit/cli/status.py
ai_journal_kit/cli/switch_framework.py
ai_journal_kit/cli/update.py
ai_journal_kit/cli/use_journal.py
ai_journal_kit/core/__init__.py
ai_journal_kit/core/config.py
ai_journal_kit/core/journal.py
ai_journal_kit/core/manifest.py
ai_journal_kit/core/migration.py
ai_journal_kit/core/symlinks.py
ai_journal_kit/core/template_updater.py
ai_journal_kit/core/templates.py
ai_journal_kit/core/validation.py
ai_journal_kit/templates/WELCOME.md
ai_journal_kit/templates/__init__.py
ai_journal_kit/templates/daily-template.md
ai_journal_kit/templates/memory-template.md
ai_journal_kit/templates/people-template.md
ai_journal_kit/templates/project-template.md
ai_journal_kit/templates/frameworks/__init__.py
ai_journal_kit/templates/frameworks/bullet-journal/__init__.py
ai_journal_kit/templates/frameworks/bullet-journal/collection-template.md
ai_journal_kit/templates/frameworks/bullet-journal/daily-template.md
ai_journal_kit/templates/frameworks/bullet-journal/future-log-template.md
ai_journal_kit/templates/frameworks/bullet-journal/monthly-template.md
ai_journal_kit/templates/frameworks/gtd/__init__.py
ai_journal_kit/templates/frameworks/gtd/daily-template.md
ai_journal_kit/templates/frameworks/gtd/project-template.md
ai_journal_kit/templates/frameworks/gtd/someday-maybe-template.md
ai_journal_kit/templates/frameworks/gtd/waiting-for-template.md
ai_journal_kit/templates/frameworks/para/__init__.py
ai_journal_kit/templates/frameworks/para/area-template.md
ai_journal_kit/templates/frameworks/para/daily-template.md
ai_journal_kit/templates/frameworks/para/project-template.md
ai_journal_kit/templates/frameworks/para/resource-template.md
ai_journal_kit-1.1.1.dist-info/METADATA
ai_journal_kit-1.1.1.dist-info/WHEEL
ai_journal_kit-1.1.1.dist-info/entry_points.txt
ai_journal_kit-1.1.1.dist-info/licenses/LICENSE
ai_journal_kit-1.1.1.dist-info/RECORD
